NikeCA.py
NikeQA.py
NikeSF.py
SnowflakeData.py
_BuildSearchQuery.py
_GitHub.py
_IMPSummaryDashboard.py
_QA.py
_SearchFiles.py
_SnowflakeData.py
_SnowflakeDependencies.py
_SnowflakePull.py
__init__.py
CADPR-0.1.1.dist-info/LICENSE
CADPR-0.1.1.dist-info/METADATA
CADPR-0.1.1.dist-info/WHEEL
CADPR-0.1.1.dist-info/top_level.txt
CADPR-0.1.1.dist-info/RECORD
